pasgen/__init__.py
pasgen/__version__.py
pasgen/core.py
pasgen/pexceptions.py
pasgen-0.5.dist-info/licenses/LICENCE
test/__init__.py
test/test_mix.py
pasgen-0.5.dist-info/METADATA
pasgen-0.5.dist-info/WHEEL
pasgen-0.5.dist-info/top_level.txt
pasgen-0.5.dist-info/RECORD
