Metadata-Version: 2.4
Name: pasgen
Version: 0.5
Summary: Password Generator For Python
Home-page: https://github.com/yavuzkanat/PasGen
Author: ahmetyavuzkanat@outlook.com
License: MIT
Classifier: Programming Language :: Python :: 3
Classifier: License :: OSI Approved :: MIT License
Requires-Python: >=3.6
License-File: LICENCE
Dynamic: author
Dynamic: classifier
Dynamic: description
Dynamic: description-content-type
Dynamic: home-page
Dynamic: license
Dynamic: license-file
Dynamic: requires-python
Dynamic: summary
